{"type":"gif","metadata":{"alias":["红温","爆炸"],"preview":"./8.png","apiVersion":101},"elements":[{"type":"image","key":"to","coords":[["0vw","0vh","100vw","100vh"],["-2vw","-2vh","104vw","104vh"],["-4vw","-4vh","108vw","108vh"],["-5vw","-5vh","110vw","110vh"],["-8vw","-7vh","113vw","114vh"],["-8vw","-9vh","119vw","118vh"],["-13vw","-10vh","120vw","123vh"],["-14vw","-13vh","125vw","126vh"],["-12vw","-14vh","130vw","128vh"],["-19vw","-16vh","129vw","132vh"],["-19vw","-15vh","135vw","139vh"],["-18vw","-22vh","142vw","138vh"],["-19vw","-22vh","147vw","144vh"],["-26vw","-23vh","143vw","146vh"],["-22vw","-30vh","153vw","145vh"],["-27vw","-30vh","154vw","151vh"],["-23vw","-30vh","164vw","157vh"],["-37vw","-32vh","156vw","161vh"]],"end":17},{"type":"image","src":"./","coords":[[0,0,"100vw","100vh"],[0,0,"100vw","100vh"],[0,0,"100vw","100vh"],[0,0,"100vw","100vh"],[0,0,"100vw","100vh"],[0,0,"100vw","100vh"],[0,0,"100vw","100vh"],[0,0,"100vw","100vh"],[0,0,"100vw","100vh"],[0,0,"100vw","100vh"],[0,0,"100vw","100vh"],[0,0,"100vw","100vh"]],"fit":"cover","start":18},{"type":"image","src":"./red.png","coords":["0vw","0vh","100vw","100vh"],"opacity":[0,0.03,0.06,0.09,0.12,0.15,0.18,0.21,0.24,0.27,0.3,0.33,0.36,0.39,0.42,0.45,0.48,0.51],"end":17}],"canvas":{"width":"min(282/to_width, 282/to_height) * to_width","height":"min(282/to_width, 282/to_height) * to_height"},"delay":[110,107,104,101,98,95,92,89,86,83,80,77,74,71,68,65,62,59,140,140,140,140,140,140,140,140,140,140,140,140]}